hyperfair/__init__.py
hyperfair/data_loader.py
hyperfair/hyperfair.py
hyperfair/mc_algo.py
hyperfair/plotting.py
hyperfair-0.1.3.dist-info/licenses/LICENSE
hyperfair-0.1.3.dist-info/METADATA
hyperfair-0.1.3.dist-info/WHEEL
hyperfair-0.1.3.dist-info/top_level.txt
hyperfair-0.1.3.dist-info/RECORD
