Metadata-Version: 2.4
Name: hyperfair
Version: 0.1.3
Summary: A Python library for generating, evaluating, and improving rankings under fairness constraints.
Author-email: Mauritz Cartier van Dissel <cartiervandissel@csh.ac.at>, Samuel Martin-Gutierrez <martin.gutierrez@csh.ac.at>, Lisette Espin-Noboa <espin@csh.ac.at>, Ana Maria Jaramillo <jaramillo@csh.ac.at>, Fariba Karimi <karimi@csh.ac.at>
Maintainer-email: Mauritz Cartier van Dissel <cartiervandissel@csh.ac.at>
License-Expression: MIT
Project-URL: Repository, https://github.com/CSHVienna/hyper_fair
Keywords: algorithmic fairness,group fairness,bias in computer systems,ranking,top-k selection,hypergeometric distribution
Classifier: Programming Language :: Python :: 3
Requires-Python: >=3.9
License-File: LICENSE
Requires-Dist: pandas
Requires-Dist: numpy
Requires-Dist: matplotlib
Requires-Dist: scipy
Dynamic: license-file
